zigpy/__init__.py
zigpy/appdb.py
zigpy/application.py
zigpy/device.py
zigpy/endpoint.py
zigpy/exceptions.py
zigpy/group.py
zigpy/util.py
zigpy/ota/__init__.py
zigpy/ota/image.py
zigpy/ota/provider.py
zigpy/profiles/__init__.py
zigpy/profiles/zha.py
zigpy/profiles/zll.py
zigpy/quirks/__init__.py
zigpy/quirks/registry.py
zigpy/types/__init__.py
zigpy/types/basic.py
zigpy/types/named.py
zigpy/types/struct.py
zigpy/zcl/__init__.py
zigpy/zcl/foundation.py
zigpy/zcl/clusters/__init__.py
zigpy/zcl/clusters/closures.py
zigpy/zcl/clusters/general.py
zigpy/zcl/clusters/homeautomation.py
zigpy/zcl/clusters/hvac.py
zigpy/zcl/clusters/lighting.py
zigpy/zcl/clusters/lightlink.py
zigpy/zcl/clusters/manufacturer_specific.py
zigpy/zcl/clusters/measurement.py
zigpy/zcl/clusters/protocol.py
zigpy/zcl/clusters/security.py
zigpy/zcl/clusters/smartenergy.py
zigpy/zdo/__init__.py
zigpy/zdo/types.py
zigpy_homeassistant-0.19.0.dist-info/COPYING
zigpy_homeassistant-0.19.0.dist-info/LICENSE
zigpy_homeassistant-0.19.0.dist-info/METADATA
zigpy_homeassistant-0.19.0.dist-info/WHEEL
zigpy_homeassistant-0.19.0.dist-info/top_level.txt
zigpy_homeassistant-0.19.0.dist-info/RECORD
